sqlite_rx/__init__.py
sqlite_rx/auth.py
sqlite_rx/backup.py
sqlite_rx/client.py
sqlite_rx/exception.py
sqlite_rx/server.py
sqlite_rx/cli/__init__.py
sqlite_rx/cli/client.py
sqlite_rx/cli/server.py
sqlite_rx/tests/__init__.py
sqlite_rx/tests/backup/__init__.py
sqlite_rx/tests/backup/conftest.py
sqlite_rx/tests/backup/test_queries.py
sqlite_rx/tests/curezmq/__init__.py
sqlite_rx/tests/curezmq/conftest.py
sqlite_rx/tests/curezmq/test_queries.py
sqlite_rx/tests/error/__init__.py
sqlite_rx/tests/error/conftest.py
sqlite_rx/tests/error/test_connection.py
sqlite_rx/tests/misc/__init__.py
sqlite_rx/tests/misc/test_backup_exception.py
sqlite_rx/tests/misc/test_curvekeygen.py
sqlite_rx/tests/plain/__init__.py
sqlite_rx/tests/plain/conftest.py
sqlite_rx/tests/plain/test_queries.py
sqlite_rx/tests/zap/__init__.py
sqlite_rx/tests/zap/conftest.py
sqlite_rx/tests/zap/test_queries.py
sqlite_rx-1.2.2.data/scripts/curve-keygen
sqlite_rx-1.2.2.dist-info/LICENSE
sqlite_rx-1.2.2.dist-info/METADATA
sqlite_rx-1.2.2.dist-info/WHEEL
sqlite_rx-1.2.2.dist-info/entry_points.txt
sqlite_rx-1.2.2.dist-info/top_level.txt
sqlite_rx-1.2.2.dist-info/RECORD
