Metadata-Version: 2.1
Name: sqlite_rx
Version: 1.2.2
Summary: Python SQLite Client and Server
Home-page: https://github.com/aosingh/sqlite_rx
Author: Abhishek Singh
Author-email: abhishek.singh20141@gmail.com
Maintainer: Abhishek Singh
Maintainer-email: abhishek.singh20141@gmail.com
License: MIT License
Project-URL: Documentation, https://aosingh.github.io/sqlite_rx/
Project-URL: Source, https://github.com/aosingh/sqlite_rx
Project-URL: Bug Tracker, https://github.com/aosingh/sqlite_rx/issues
Project-URL: CI, https://github.com/aosingh/sqlite_rx/actions
Project-URL: Release Notes, https://github.com/aosingh/sqlite_rx/releases
Project-URL: License, https://github.com/aosingh/sqlite_rx/blob/master/LICENSE
Keywords: sqlite client server fast secure
Classifier: Topic :: Database :: Database Engines/Servers
Classifier: Development Status :: 5 - Production/Stable
Classifier: Intended Audience :: Education
Classifier: Intended Audience :: Developers
Classifier: Intended Audience :: Science/Research
Classifier: Intended Audience :: System Administrators
Classifier: License :: OSI Approved :: MIT License
Classifier: Programming Language :: Python :: 3 :: Only
Classifier: Programming Language :: Python :: 3.8
Classifier: Programming Language :: Python :: 3.9
Classifier: Programming Language :: Python :: 3.10
Classifier: Programming Language :: Python :: 3.11
Classifier: Programming Language :: Python :: 3.12
Classifier: Programming Language :: Python :: 3.13
Classifier: Operating System :: POSIX :: Linux
Classifier: Operating System :: Unix
Classifier: Operating System :: Microsoft :: Windows
Classifier: Operating System :: MacOS
Requires-Python: >=3.8
License-File: LICENSE
Requires-Dist: msgpack==1.1.0
Requires-Dist: pyzmq==26.2.0
Requires-Dist: tornado==6.4.2
Requires-Dist: billiard==4.2.1
Provides-Extra: cli
Requires-Dist: click==8.1.7; extra == "cli"
Requires-Dist: rich==13.9.3; extra == "cli"
Requires-Dist: pygments==2.18.0; extra == "cli"
